AnsIndex/AnsIndex.py
AnsIndex/__init__.py
AnsIndex-0.2.dist-info/LICENSE
AnsIndex-0.2.dist-info/METADATA
AnsIndex-0.2.dist-info/WHEEL
AnsIndex-0.2.dist-info/top_level.txt
AnsIndex-0.2.dist-info/RECORD
